CHANGES.rst
CONTRIBUTORS.rst
DEVELOP.rst
LICENSE.GPL
LICENSE.rst
MANIFEST.in
README.rst
setup.cfg
setup.py
docs/conf.py
docs/index.rst
src/cybro/__init__.py
src/cybro.usergroup.shift.egg-info/PKG-INFO
src/cybro.usergroup.shift.egg-info/SOURCES.txt
src/cybro.usergroup.shift.egg-info/dependency_links.txt
src/cybro.usergroup.shift.egg-info/entry_points.txt
src/cybro.usergroup.shift.egg-info/namespace_packages.txt
src/cybro.usergroup.shift.egg-info/not-zip-safe
src/cybro.usergroup.shift.egg-info/requires.txt
src/cybro.usergroup.shift.egg-info/top_level.txt
src/cybro/usergroup/__init__.py
src/cybro/usergroup/shift/__init__.py
src/cybro/usergroup/shift/interfaces.py
src/cybro/usergroup/shift/setuphandlers.py
src/cybro/usergroup/shift/controlpanels/__init__.py
src/cybro/usergroup/shift/controlpanels/user_group_shift_control_panel/__init__.py
src/cybro/usergroup/shift/controlpanels/user_group_shift_control_panel/controlpanel.py